ncem/__init__.py
ncem/__main__.py
ncem/api/__init__.py
ncem/api/train/__init__.py
ncem/data.py
ncem/estimators/__init__.py
ncem/estimators/base_estimator.py
ncem/estimators/base_estimator_neighbors.py
ncem/estimators/estimator_cvae.py
ncem/estimators/estimator_cvae_ncem.py
ncem/estimators/estimator_deconvolution.py
ncem/estimators/estimator_ed.py
ncem/estimators/estimator_ed_ncem.py
ncem/estimators/estimator_interactions.py
ncem/estimators/estimator_linear.py
ncem/interpretation/__init__.py
ncem/interpretation/interpreter.py
ncem/models/__init__.py
ncem/models/custom_callbacks.py
ncem/models/layers/__init__.py
ncem/models/layers/gnn_layers.py
ncem/models/layers/layer_stacks_lvm.py
ncem/models/layers/output_layers.py
ncem/models/layers/preproc_input.py
ncem/models/layers/single_gnn_layers.py
ncem/models/model_cvae.py
ncem/models/model_cvae_ncem.py
ncem/models/model_ed.py
ncem/models/model_ed_ncem.py
ncem/models/model_ed_single_ncem.py
ncem/models/model_interactions.py
ncem/models/model_linear.py
ncem/pl/__init__.py
ncem/pl/ablation.py
ncem/pl/input.py
ncem/pl/type_couplings.py
ncem/py.typed
ncem/tl/__init__.py
ncem/tl/fit/__init__.py
ncem/tl/fit/backend/__init__.py
ncem/tl/fit/backend/ablation.py
ncem/tl/fit/backend/design_matrix.py
ncem/tl/fit/backend/linear_model.py
ncem/tl/fit/backend/ols_fit.py
ncem/tl/fit/backend/spline_model.py
ncem/tl/fit/backend/testing.py
ncem/tl/fit/backend/utils.py
ncem/tl/fit/backend/vardecomp.py
ncem/tl/fit/constants.py
ncem/tl/fit/glm/__init__.py
ncem/tl/fit/tf/__init__.py
ncem/tl/fit/torch/__init__.py
ncem/train/__init__.py
ncem/train/summaries.py
ncem/train/train_model.py
ncem/unit_test/__init__.py
ncem/unit_test/data_for_tests.py
ncem/unit_test/directories.py
ncem/unit_test/test_dataloader_local.py
ncem/unit_test/test_estimator_local.py
ncem/unit_test/tools/__init__.py
ncem/unit_test/tools/fit/__init__.py
ncem/unit_test/tools/fit/test_glm.py
ncem/unit_test/tools/fit/test_spline.py
ncem/utils/_utils.py
ncem/utils/losses.py
ncem-0.1.5.dist-info/LICENSE
ncem-0.1.5.dist-info/METADATA
ncem-0.1.5.dist-info/WHEEL
ncem-0.1.5.dist-info/entry_points.txt
ncem-0.1.5.dist-info/RECORD
