Metadata-Version: 2.1
Name: ncem
Version: 0.1.5
Summary: ncem. Learning cell communication from spatial graphs of cells.
Home-page: https://github.com/theislab/ncem
License: BSD
Author: Anna C. Schaar
Author-email: anna.schaar@helmholtz-muenchen.de
Requires-Python: >=3.8,<=3.10
Classifier: License :: Other/Proprietary License
Classifier: Programming Language :: Python :: 3
Classifier: Programming Language :: Python :: 3.8
Classifier: Programming Language :: Python :: 3.9
Classifier: Programming Language :: Python :: 3.10
Requires-Dist: Jinja2 (>=2.11.3,<4.0.0)
Requires-Dist: PyYAML (>=5.4.1,<6.0.0)
Requires-Dist: click (>=8.0.0,<9.0.0)
Requires-Dist: diffxpy (>=0.7.4,<0.8.0)
Requires-Dist: docrep (>=0.3.2,<0.4.0)
Requires-Dist: joblib (>=1.2.0,<2.0.0)
Requires-Dist: louvain (>=0.7.0,<0.8.0)
Requires-Dist: matplotlib (>=3.7.1,<4.0.0)
Requires-Dist: numpy (>=1.22)
Requires-Dist: patsy (>=0.5.1,<0.6.0)
Requires-Dist: rich (>=10.1.0,<11.0.0)
Requires-Dist: scanpy (>=1.9.3,<2.0.0)
Requires-Dist: scipy (==1.9.1)
Requires-Dist: seaborn (>=0.12.2,<0.13.0)
Requires-Dist: squidpy (>=1.2.3,<2.0.0)
Requires-Dist: tensorflow (>=2.11.1,<3.0.0)
Project-URL: Documentation, https://ncem.readthedocs.io
Project-URL: Repository, https://github.com/theislab/ncem
